Metadata-Version: 2.2
Name: titanfp
Version: 0.1.1
Summary: number systems research with FPBench, including implementation of posits
Author-email: Bill Zorn <billzorn@cs.washington.edu>, Brett Saiki <bsaiki@cs.washington.edu>
License: MIT License
Project-URL: Homepage, https://github.com/billzorn/titanic
Project-URL: Issues, https://github.com/billzorn/titanic/issues
Classifier: Development Status :: 3 - Alpha
Classifier: Programming Language :: Python :: 3
Classifier: License :: OSI Approved :: MIT License
Classifier: Operating System :: POSIX :: Linux
License-File: LICENSE
Requires-Dist: numpy>=2.1
Requires-Dist: gmpy2>=2.2
Requires-Dist: antlr4-python3-runtime~=4.9.3
